drf_advanced_auth/__init__.py
drf_advanced_auth/apps.py
drf_advanced_auth/conf.py
drf_advanced_auth/serializers.py
drf_advanced_auth/urls.py
drf_advanced_auth/utils.py
drf_advanced_auth/views.py
sample_app/__init__.py
sample_app/authentication.py
sample_app/models.py
sample_app/settings.py
sample_app/urls.py
sample_app/migrations/0001_initial.py
sample_app/migrations/__init__.py
tests/__init__.py
tests/test_conf.py
tests/test_misc.py
tests/test_views.py
tests/utils.py
drf_advanced_auth-0.4.0.dist-info/LICENSE
drf_advanced_auth-0.4.0.dist-info/METADATA
drf_advanced_auth-0.4.0.dist-info/WHEEL
drf_advanced_auth-0.4.0.dist-info/top_level.txt
drf_advanced_auth-0.4.0.dist-info/RECORD
