Metadata-Version: 2.1
Name: drf-advanced-auth
Version: 0.4.0
Summary: Full authentication and credential management for Django REST Framework
Home-page: https://github.com/seawolf42/drf-advanced-auth
Author: jeffrey k eliasen
Author-email: jeff+drf-advanced-auth@jke.net
License: MIT License
Keywords: drf-advanced-auth
Platform: UNKNOWN
Classifier: Framework :: Django
Classifier: Framework :: Django :: 2.0
Classifier: Framework :: Django :: 3.0
Classifier: Intended Audience :: Developers
Classifier: License :: OSI Approved :: MIT License
Classifier: Natural Language :: English
Classifier: Programming Language :: Python :: 3
Classifier: Programming Language :: Python :: 3.5
Classifier: Programming Language :: Python :: 3.6
Requires-Dist: Django (>=2.0)
